hyperworks_tools/__init__.py
hyperworks_tools/cli/__init__.py
hyperworks_tools/cli/post_cmds.py
hyperworks_tools/cli/root.py
hyperworks_tools/post/__init__.py
hyperworks_tools/post/datastructure/__init__.py
hyperworks_tools/post/datastructure/outfile.py
hyperworks_tools/post/datastructure/test_outfile.py
hyperworks_tools/post/outfile_extractor.py
hyperworks_tools/post/test_outfile_extractor.py
hyperworks_tools-0.1.0.dist-info/entry_points.txt
hyperworks_tools-0.1.0.dist-info/METADATA
hyperworks_tools-0.1.0.dist-info/WHEEL
hyperworks_tools-0.1.0.dist-info/LICENSE
hyperworks_tools-0.1.0.dist-info/RECORD
