Metadata-Version: 2.1
Name: hyperworks-tools
Version: 0.1.0
Summary: 
License: MIT
Author: Manuel
Author-email: manuel.ramsaier89@gmail.com
Requires-Python: >=3.8.9,<4.0.0
Classifier: License :: OSI Approved :: MIT License
Classifier: Programming Language :: Python :: 3
Classifier: Programming Language :: Python :: 3.9
Classifier: Programming Language :: Python :: 3.10
Classifier: Programming Language :: Python :: 3.11
Requires-Dist: typer[all] (>=0.7.0,<0.8.0)
